dolarhoy/__init__.py
tests/__init__.py
tests/test_dolarhoy.py
dolarhoy-0.0.3.dist-info/LICENSE
dolarhoy-0.0.3.dist-info/METADATA
dolarhoy-0.0.3.dist-info/WHEEL
dolarhoy-0.0.3.dist-info/top_level.txt
dolarhoy-0.0.3.dist-info/RECORD
