Metadata-Version: 2.1
Name: dolarhoy
Version: 0.0.3
Summary: DolarHoy es una librería en Python que facilita la obtención de cotizaciones actualizadas de diferentes tipos de dólar en Argentina, utilizando web scraping para extraer datos del sitio web DolarHoy.
Home-page: https://github.com/torrresagus/DolarHoy
Author: Agustin Torres
Author-email: agustintorres2001@outlook.com.ar
Keywords: python,dolar,dolarhoy,DolarHoy,web scraping,exchange rates,cotizaciones,dollar rates,argentina,financial data,beautifulsoup,requests
Classifier: Development Status :: 3 - Alpha
Classifier: Intended Audience :: Developers
Classifier: Topic :: Software Development :: Libraries :: Python Modules
Classifier: License :: OSI Approved :: MIT License
Classifier: Programming Language :: Python :: 3
Classifier: Operating System :: OS Independent
License-File: LICENSE
Requires-Dist: requests
Requires-Dist: beautifulsoup4
